nexradaws2/__init__.py
nexradaws2/nexradawsinterface.py
nexradaws2/resources/__init__.py
nexradaws2/resources/awsnexradfile.py
nexradaws2/resources/downloadresults.py
nexradaws2/resources/localnexradfile.py
nexradaws2-2.1.dist-info/LICENSE
nexradaws2-2.1.dist-info/METADATA
nexradaws2-2.1.dist-info/WHEEL
nexradaws2-2.1.dist-info/top_level.txt
nexradaws2-2.1.dist-info/RECORD
