Metadata-Version: 2.1
Name: nexradaws2
Version: 2.1
Summary: Query and download NEXRAD data from AWS S3 storage.
Home-page: https://github.com/aarande/nexradaws
Author: Aaron Anderson, Aareon Sullivan
Author-email: aaron.anderson74@yahoo.com
License: MIT
Download-URL: https://github.com/Aareon/nexradaws/archive/2.0.tar.gz
Keywords: weather,radar,nexrad,aws,amazon
Platform: UNKNOWN
Classifier: Development Status :: 5 - Production/Stable
Classifier: Intended Audience :: Science/Research
Classifier: License :: OSI Approved :: MIT License
Classifier: Topic :: Scientific/Engineering :: Atmospheric Science
Classifier: Programming Language :: Python :: 2.7
Classifier: Programming Language :: Python :: 3
License-File: LICENSE
Requires-Dist: boto3
Requires-Dist: pytz
Requires-Dist: six
